{
  "updated_at": "2026-05-19T21:12:22.049372+00:00",
  "players": [
    {
      "name": "Squirt1e",
      "tag": "2004",
      "url": "https://lol.ps/summoner/Squirt1e%20_2004?region=kr",
      "tier": "Master",
      "lp": 586,
      "lp_diff": -22,
      "wins": 110,
      "losses": 100,
      "winrate": 52.4,
      "rank": 1
    },
    {
      "name": "マチュ",
      "tag": "KR2",
      "url": "https://lol.ps/summoner/%E3%83%9E%E3%83%81%E3%83%A5%20_KR2?region=kr",
      "tier": "Master",
      "lp": 308,
      "lp_diff": 20,
      "wins": 80,
      "losses": 65,
      "winrate": 55.2,
      "rank": 2
    },
    {
      "name": "leave me alone",
      "tag": "2005",
      "url": "https://lol.ps/summoner/leave%20me%20alone%20_2005?region=kr",
      "tier": "Master",
      "lp": 285,
      "lp_diff": 2,
      "wins": 60,
      "losses": 47,
      "winrate": 56.1,
      "rank": 3
    }
  ]
}