{
  "updated_at": "2026-05-28T18:43:20.798544+00:00",
  "players": [
    {
      "name": "Squirt1e",
      "tag": "2004",
      "url": "https://lol.ps/summoner/Squirt1e%20_2004?region=kr",
      "tier": "Master",
      "lp": 568,
      "lp_diff": 18,
      "wins": 115,
      "losses": 107,
      "winrate": 51.8,
      "rank": 1
    },
    {
      "name": "マチュ",
      "tag": "KR2",
      "url": "https://lol.ps/summoner/%E3%83%9E%E3%83%81%E3%83%A5%20_KR2?region=kr",
      "tier": "Master",
      "lp": 327,
      "lp_diff": 19,
      "wins": 81,
      "losses": 65,
      "winrate": 55.5,
      "rank": 2
    },
    {
      "name": "leave me alone",
      "tag": "2005",
      "url": "https://lol.ps/summoner/leave%20me%20alone%20_2005?region=kr",
      "tier": "Master",
      "lp": 232,
      "lp_diff": -18,
      "wins": 65,
      "losses": 55,
      "winrate": 54.2,
      "rank": 3
    }
  ]
}